pyaml_env/__init__.py
pyaml_env/base_config.py
pyaml_env/parse_config.py
pyaml_env-1.2.1.dist-info/LICENSE
pyaml_env-1.2.1.dist-info/METADATA
pyaml_env-1.2.1.dist-info/WHEEL
pyaml_env-1.2.1.dist-info/top_level.txt
pyaml_env-1.2.1.dist-info/RECORD
