Metadata-Version: 2.1
Name: pyaml_env
Version: 1.2.1
Summary: Provides yaml file parsing with environment variable resolution
Home-page: https://github.com/mkaranasou/pyaml_env
Author: Maria Karanasou
Author-email: karanasou@gmail.com
Project-URL: Bug Tracker, https://github.com/mkaranasou/pyaml_env/issues
Classifier: Programming Language :: Python :: 3
Classifier: License :: OSI Approved :: MIT License
Classifier: Operating System :: OS Independent
Requires-Python: >=3.6
Provides-Extra: test
License-File: LICENSE
